pyabc12345678/__init__.py
pyabc12345678-0.6.dist-info/LICENSE.txt
pyabc12345678-0.6.dist-info/METADATA
pyabc12345678-0.6.dist-info/WHEEL
pyabc12345678-0.6.dist-info/top_level.txt
pyabc12345678-0.6.dist-info/RECORD
